sar_sdk/__init__.py
sar_sdk/module.py
sar_sdk-0.1.0.dist-info/METADATA
sar_sdk-0.1.0.dist-info/WHEEL
sar_sdk-0.1.0.dist-info/top_level.txt
sar_sdk-0.1.0.dist-info/RECORD
