Metadata-Version: 2.1
Name: sar_sdk
Version: 0.1.0
Summary: Python SDK for controlling SAR grippers over TCP
Author-email: Dexsent Robotics <dexsentrobotics@gmail.com>
License: Proprietary - Sastra Innovation Labs
Project-URL: Homepage, https://github.com/dexsent/sar_sdk
Project-URL: Documentation, https://github.com/dexsent/sar_sdk/wiki
Requires-Python: >=3.7
